<?xml version="1.0" encoding="utf-8"?>
<abapGit version="v1.0.0" serializer="LCL_OBJECT_TOBJ" serializer_version="v1.0.0">
 <asx:abap xmlns:asx="http://www.sap.com/abapxml" version="1.0">
  <asx:values>
   <OBJH>
    <OBJECTNAME>ZMMMV_T001W</OBJECTNAME>
    <OBJECTTYPE>V</OBJECTTYPE>
    <CLIDEP>X</CLIDEP>
    <OBJCATEG>CUST</OBJCATEG>
    <OBJTRANSP>2</OBJTRANSP>
    <OBJHASADDR>X</OBJHASADDR>
    <IMPORTABLE>3</IMPORTABLE>
   </OBJH>
   <OBJT>
    <LANGUAGE>E</LANGUAGE>
    <OBJECTNAME>ZMMMV_T001W</OBJECTNAME>
    <OBJECTTYPE>V</OBJECTTYPE>
    <DDTEXT>Plants</DDTEXT>
   </OBJT>
   <OBJS>
    <OBJS>
     <OBJECTNAME>ZMMMV_T001W</OBJECTNAME>
     <OBJECTTYPE>V</OBJECTTYPE>
     <TABNAME>T001W</TABNAME>
     <DDIC>X</DDIC>
     <PRIM_TABLE>X</PRIM_TABLE>
    </OBJS>
   </OBJS>
   <TOBJ>
    <TDDAT>
     <TABNAME>ZMMMV_T001W</TABNAME>
     <CCLASS>ZMM</CCLASS>
    </TDDAT>
    <TVDIR>
     <TABNAME>ZMMMV_T001W</TABNAME>
     <AREA>ZMM_TG_T001W</AREA>
     <TYPE>2</TYPE>
     <LISTE>9000</LISTE>
     <DETAIL>9001</DETAIL>
    </TVDIR>
   </TOBJ>
  </asx:values>
 </asx:abap>
</abapGit>
